geopoz/__init__.py
geopoz/blocks.py
geopoz/clusters.py
geopoz/dataloader.py
geopoz/plotting.py
geopoz/stats.py
geopoz/tert.py
geopoz/data/ames.geojson
geo_lyb-0.0.5.dist-info/METADATA
geo_lyb-0.0.5.dist-info/WHEEL
geo_lyb-0.0.5.dist-info/top_level.txt
geo_lyb-0.0.5.dist-info/RECORD
