Metadata-Version: 2.1
Name: geo-lyb
Version: 0.0.5
Summary: wood class
Home-page: https://github.com/WalidGharianiEAGLE/geo-poz
Author: Walid Ghariani
Author-email: walid11ghariani@gmail.com
License: MIT
Keywords: spatial
Classifier: Development Status :: 3 - Alpha
Classifier: Intended Audience :: Science/Research
Classifier: License :: OSI Approved :: MIT License
Classifier: Programming Language :: Python :: 3
Classifier: Programming Language :: Python :: 3.7
Classifier: Programming Language :: Python :: 3.8
Classifier: Programming Language :: Python :: 3.9
Requires-Python: >=3.7
Requires-Dist: pandas (>=0.20)
Requires-Dist: numpy (>=1.10.0)
Requires-Dist: geopandas (>=0.3)
Requires-Dist: shapely (>=1.6)
Requires-Dist: matplotlib (>=2.2.4)
Requires-Dist: scikit-learn (>=0.22)
